remt/__init__.py
remt/cmd.py
remt/const.py
remt/data.py
remt/drawer.py
remt/error.py
remt/indexer.py
remt/meta.py
remt/parser.py
remt/pdf.py
remt/py.typed
remt/tool.py
remt/util.py
remt/tests/__init__.py
remt/tests/test_cmd.py
remt/tests/test_data.py
remt/tests/test_indexer.py
remt/tests/test_meta.py
remt/tests/test_parser.py
remt/tests/test_tool.py
remt/tests/test_util.py
remt-0.10.1.data/scripts/remt
remt-0.10.1.dist-info/COPYING
remt-0.10.1.dist-info/METADATA
remt-0.10.1.dist-info/WHEEL
remt-0.10.1.dist-info/top_level.txt
remt-0.10.1.dist-info/RECORD
