Metadata-Version: 2.1
Name: remt
Version: 0.10.1
Summary: remt - note-taking support tool for reMarkable tablet
Home-page: https://wrobell.dcmod.org/remt/
Author: Artur Wroblewski
Author-email: wrobell@riseup.net
License: GPLv3+
Project-URL: Source Code, https://gitlab.com/wrobell/remt
Project-URL: Bug tracker, https://gitlab.com/wrobell/remt/issues
Keywords: remarkable,tools
Platform: UNKNOWN
Classifier: License :: OSI Approved :: GNU General Public License v3 or later (GPLv3+)
Classifier: Programming Language :: Python :: 3
Classifier: Development Status :: 4 - Beta
Classifier: Topic :: Multimedia :: Graphics
Classifier: Topic :: Scientific/Engineering
Requires-Python: >=3.9
License-File: COPYING
Requires-Dist: pygobject
Requires-Dist: pycairo
Requires-Dist: asyncssh
Requires-Dist: cytoolz
Requires-Dist: iterfzf
Requires-Dist: getmac
Provides-Extra: tests
Requires-Dist: mypy (>=0.930) ; extra == 'tests'
Requires-Dist: flake8 ; extra == 'tests'
Requires-Dist: pytest-cov ; extra == 'tests'
Requires-Dist: pytest-timeout ; extra == 'tests'
Requires-Dist: pytest-asyncio ; extra == 'tests'
Requires-Dist: uvloop ; extra == 'tests'
Requires-Dist: types-pkg-resources ; extra == 'tests'
Requires-Dist: types-setuptools ; extra == 'tests'
